MANIFEST.in
README.rst
example.py
setup.py
ader/__init__.py
ader/utils.py
ader.egg-info/PKG-INFO
ader.egg-info/SOURCES.txt
ader.egg-info/dependency_links.txt
ader.egg-info/requires.txt
ader.egg-info/top_level.txt
ader/dg/__init__.py
ader/dg/convergence.py
ader/dg/initial_guess.py
ader/dg/matrices.py
ader/etc/__init__.py
ader/etc/autodiff.py
ader/etc/basis.py
ader/etc/boundaries.py
ader/fv/__init__.py
ader/fv/fluxes.py
ader/fv/utils.py
ader/weno/__init__.py
ader/weno/utils.py