Metadata-Version: 1.1
Name: ader
Version: 1.2.1
Summary: The ADER method for solving any (potentially very stiff) hyperbolic system of PDEs
Home-page: https://github.com/haranjackson/ADER
Author: Haran Jackson
Author-email: jackson.haran@gmail.com
License: MIT
Download-URL: https://github.com/haranjackson/ADER/archive/1.2.0.tar.gz
Keywords: ADER,WENO,Discontinuous Galerkin,Finite Volume,PDEs,Partial Differential Equations
Platform: UNKNOWN
Classifier: Intended Audience :: Science/Research
Classifier: License :: OSI Approved :: MIT License
Classifier: Programming Language :: Python :: 3.6
Classifier: Topic :: Scientific/Engineering :: Atmospheric Science
Classifier: Topic :: Scientific/Engineering :: Chemistry
Classifier: Topic :: Scientific/Engineering :: Mathematics
Classifier: Topic :: Scientific/Engineering :: Physics
